mdps_app_generator-1.1.1.dist-info/licenses/LICENSE.txt
unity_app_generator/__init__.py
unity_app_generator/__main__.py
unity_app_generator/ecr_helper.py
unity_app_generator/generator.py
unity_app_generator/interface.py
unity_app_generator/state.py
unity_app_generator/version.py
mdps_app_generator-1.1.1.dist-info/METADATA
mdps_app_generator-1.1.1.dist-info/WHEEL
mdps_app_generator-1.1.1.dist-info/entry_points.txt
mdps_app_generator-1.1.1.dist-info/top_level.txt
mdps_app_generator-1.1.1.dist-info/RECORD
