Metadata-Version: 2.4
Name: mdps_app_generator
Version: 1.1.1
Summary: Generates an OGC compliant Unity application package using the Unity app-pack-generator.
Author: James McDuffie
License: Apache License
Keywords: unity-sds,ogc,packaging,cwl,jupyter
Classifier: Development Status :: 4 - Beta
Classifier: Environment :: Console
Classifier: Intended Audience :: Developers
Classifier: License :: OSI Approved :: MIT License
Classifier: Natural Language :: English
Classifier: Operating System :: OS Independent
Classifier: Programming Language :: Python :: 3 :: Only
Classifier: Topic :: Software Development :: Build Tools
Classifier: Topic :: Utilities
Requires-Python: >=3.9
License-File: LICENSE.txt
Requires-Dist: boto3
Requires-Dist: app_pack_generator>=1.1.0
Requires-Dist: unity-sds-client>=0.2.0
Dynamic: license-file
